devvapi/__init__.py
devvapi/__main__.py
devvapi/apps/__init__.py
devvapi/apps/core.py
devvapi/base/__init__.py
devvapi/base/run.py
devvapi/conf/__init__.py
devvapi/conf/main.py
devvapi/core/__init__.py
devvapi/core/management.py
devvapi/handlers/__init__.py
devvapi/handlers/request.py
devvapi/setup/devvapi.py
devvapi/setup/_dirs/__init__.py
devvapi/setup/_dirs/newversion.py
devvapi/setup/_dirs/startapp.py
devvapi/setup/_dirs/startproject.py
devvapi/setup/_write/__init__.py
devvapi/setup/_write/app.py
devvapi/setup/_write/apps.py
devvapi/setup/_write/manage.py
devvapi/setup/_write/settings.py
devvapi/setup/default/manage.py
devvapi/setup/default/app/__init__.py
devvapi/setup/default/app/app.py
devvapi/setup/default/app/views.py
devvapi/setup/default/conf/apps.py
devvapi/setup/default/conf/settings.py
devvapi-2.0.0.dist-info/LICENSE
devvapi-2.0.0.dist-info/METADATA
devvapi-2.0.0.dist-info/WHEEL
devvapi-2.0.0.dist-info/top_level.txt
devvapi-2.0.0.dist-info/RECORD
