Metadata-Version: 2.1
Name: devvapi
Version: 2.0.0
Summary: Framework for creating API
Author-email: Abdulloh <abdullohnugmonovone222@gmail.com>
Project-URL: Homepage, https://github.com/sk1llpy/devvapi
Project-URL: Issues, https://github.com/sk1llpy/devvapi/issues
Classifier: Programming Language :: Python :: 3
Classifier: License :: OSI Approved :: MIT License
Classifier: Operating System :: OS Independent
Requires-Python: >=3.6
License-File: LICENSE
